pyrebar/__init__.py
pyrebar/__main__.py
pyrebar/application.py
pyrebar/plugins.py
pyrebar/apps/__init__.py
pyrebar/apps/example.py
pyrebar/apps/minimal_example.py
pyrebar/utils/__init__.py
pyrebar/utils/logging.py
pyrebar/utils/singleton_meta.py
py_rebar-0.2.0.dist-info/LICENSE
py_rebar-0.2.0.dist-info/METADATA
py_rebar-0.2.0.dist-info/WHEEL
py_rebar-0.2.0.dist-info/top_level.txt
py_rebar-0.2.0.dist-info/RECORD
