Metadata-Version: 2.1
Name: py-rebar
Version: 0.2.0
Summary: Application framework for console-based python applications.
Author-email: Joe Reed <greyskyy@gmail.com>
License: MIT License
Project-URL: homepage, https://github.com/greyskyy/py-rebar
Project-URL: repository, https://github.com/greyskyy/py-rebar
Classifier: Development Status :: 4 - Beta
Classifier: Environment :: Console
Classifier: Environment :: Plugins
Classifier: Intended Audience :: Developers
Classifier: License :: OSI Approved :: MIT License
Classifier: Operating System :: OS Independent
Classifier: Programming Language :: Python :: 3
Classifier: Programming Language :: Python :: 3.9
Classifier: Programming Language :: Python :: 3.10
Classifier: Programming Language :: Python :: 3.11
Classifier: Programming Language :: Python :: 3.12
Classifier: Topic :: Software Development
Classifier: Topic :: Software Development :: Libraries :: Application Frameworks
Classifier: Topic :: Software Development :: Libraries :: Python Modules
Requires-Python: >=3.9
License-File: LICENSE
